setup.py
src/blancmange/__init__.py
src/blancmange/config.py
src/blancmange/creation.py
src/blancmange/models.py
src/blancmange.egg-info/PKG-INFO
src/blancmange.egg-info/SOURCES.txt
src/blancmange.egg-info/dependency_links.txt
src/blancmange.egg-info/entry_points.txt
src/blancmange.egg-info/not-zip-safe
src/blancmange.egg-info/requires.txt
src/blancmange.egg-info/top_level.txt