Metadata-Version: 1.1
Name: blancmange
Version: 0.2
Summary: Determine what's missing from Python by using Monty Python's Flying Circus.
Home-page: http://github.com/davidjb/blancmange
Author: David Beitey
Author-email: david@davidjb.com
License: UNKNOWN
Keywords: python keywords flying circus blancmange
Platform: UNKNOWN
Classifier: Programming Language :: Python
